cyminiaudio/__init__.py
cyminiaudio/_core.cpython-313-darwin.so
cyminiaudio-0.1.1.dist-info/METADATA
cyminiaudio-0.1.1.dist-info/WHEEL
cyminiaudio-0.1.1.dist-info/licenses/LICENSE
cyminiaudio-0.1.1.dist-info/RECORD
