Metadata-Version: 2.4
Name: cyminiaudio
Version: 0.1.1
Summary: Minimal Python bindings for miniaudio
Keywords: audio,sound,miniaudio,playback,recording,waveform,filters,dsp,real-time,cross-platform
Author-Email: Your Name <your.email@example.com>
Maintainer-Email: Your Name <your.email@example.com>
License-Expression: Unlicense
Classifier: Development Status :: 4 - Beta
Classifier: Intended Audience :: Developers
Classifier: Intended Audience :: Science/Research
Classifier: Operating System :: MacOS
Classifier: Operating System :: Microsoft :: Windows
Classifier: Operating System :: POSIX :: Linux
Classifier: Programming Language :: Cython
Classifier: Programming Language :: Python :: 3
Classifier: Programming Language :: Python :: 3.9
Classifier: Programming Language :: Python :: 3.10
Classifier: Programming Language :: Python :: 3.11
Classifier: Programming Language :: Python :: 3.12
Classifier: Programming Language :: Python :: 3.13
Classifier: Programming Language :: Python :: Implementation :: CPython
Classifier: Topic :: Multimedia :: Sound/Audio
Classifier: Topic :: Multimedia :: Sound/Audio :: Analysis
Classifier: Topic :: Multimedia :: Sound/Audio :: Players
Classifier: Topic :: Multimedia :: Sound/Audio :: Sound Synthesis
Classifier: Topic :: Software Development :: Libraries :: Python Modules
Classifier: Typing :: Typed
Project-URL: Homepage, https://github.com/yourusername/cyminiaudio
Project-URL: Documentation, https://github.com/yourusername/cyminiaudio#readme
Project-URL: Repository, https://github.com/yourusername/cyminiaudio.git
Project-URL: Issues, https://github.com/yourusername/cyminiaudio/issues
Project-URL: Changelog, https://github.com/yourusername/cyminiaudio/blob/main/CHANGELOG.md
Requires-Python: >=3.9
